physix/__init__.py
physix/mechanics.py
physix-0.0.2.dist-info/LICENSE
physix-0.0.2.dist-info/METADATA
physix-0.0.2.dist-info/WHEEL
physix-0.0.2.dist-info/top_level.txt
physix-0.0.2.dist-info/RECORD
