Metadata-Version: 2.1
Name: physix
Version: 0.0.2
Summary: A Physics toolbox in Python
Home-page: https://github.com/maroba/physix
Author: Matthias Baer
Author-email: matthias.r.baer@googlemail.com
License: MIT
Platform: ALL
Classifier: Operating System :: OS Independent
Classifier: Programming Language :: Python :: 3
Requires-Python: >=3.6
License-File: LICENSE
Requires-Dist: sphinx
Requires-Dist: numpy
Requires-Dist: sympy
Requires-Dist: scipy
